edc_rx/__init__.py
edc_rx/admin_site.py
edc_rx/apps.py
edc_rx/models.py
edc_rx/urls.py
edc_rx/utils.py
edc_rx/migrations/0001_initial.py
edc_rx/migrations/0002_rxmodificationreasons_extra_value_and_more.py
edc_rx/migrations/0003_alter_rxmodificationreasons_options_and_more.py
edc_rx/migrations/0004_remove_rxmodificationreasons_edc_rx_rxmo_name_b72a47_idx_and_more.py
edc_rx/migrations/__init__.py
edc_rx/model_mixins/__init__.py
edc_rx/model_mixins/drug_refill_model_mixin.py
edc_rx/model_mixins/drug_supply_model_mixin.py
edc_rx/model_mixins/treatment_pay_methods.py
edc_rx/modeladmin_mixins/__init__.py
edc_rx/modeladmin_mixins/drug_refill_admin_mixin.py
edc_rx/modeladmin_mixins/drug_supply_inline_mixin.py
edc_rx/modelform_mixins/__init__.py
edc_rx/modelform_mixins/drug_supply_ncd_modelform_mixin.py
edc_rx/tests/__init__.py
edc_rx/tests/test_settings.py
edc_rx/tests/etc/user-aes-local.key
edc_rx/tests/etc/user-aes-restricted.key
edc_rx/tests/etc/user-rsa-local-private.pem
edc_rx/tests/etc/user-rsa-local-public.pem
edc_rx/tests/etc/user-rsa-restricted-private.pem
edc_rx/tests/etc/user-rsa-restricted-public.pem
edc_rx/tests/etc/user-salt-local.key
edc_rx/tests/etc/user-salt-restricted.key
edc_rx/tests/tests/__init__.py
edc_rx/tests/tests/test_utils.py
edc_rx-1.0.1.dist-info/AUTHORS
edc_rx-1.0.1.dist-info/LICENSE
edc_rx-1.0.1.dist-info/METADATA
edc_rx-1.0.1.dist-info/WHEEL
edc_rx-1.0.1.dist-info/top_level.txt
edc_rx-1.0.1.dist-info/RECORD
